bcbio_monitor/__init__.py
bcbio_monitor/config/__init__.py
bcbio_monitor/graph/__init__.py
bcbio_monitor/log/__init__.py
bcbio_monitor/parser/__init__.py
bcbio_monitor/static/.DS_Store
bcbio_monitor/static/css/bootstrap.min.css
bcbio_monitor/static/css/monitor.css
bcbio_monitor/static/ico/favicon.ico
bcbio_monitor/static/js/moment.js
bcbio_monitor/static/js/monitor.js
bcbio_monitor/static/js/utils.js
bcbio_monitor/static/js/viz.js
bcbio_monitor/templates/404.html
bcbio_monitor/templates/base.html
bcbio_monitor/templates/index.html
bcbio_monitor-1.0.1.dist-info/DESCRIPTION.rst
bcbio_monitor-1.0.1.dist-info/METADATA
bcbio_monitor-1.0.1.dist-info/RECORD
bcbio_monitor-1.0.1.dist-info/WHEEL
bcbio_monitor-1.0.1.dist-info/entry_points.txt
bcbio_monitor-1.0.1.dist-info/metadata.json
bcbio_monitor-1.0.1.dist-info/top_level.txt
bcbio_monitor-1.0.1.dist-info/zip-safe
