Metadata-Version: 2.0
Name: bcbio-monitor
Version: 1.0.1
Summary: bcbio-monitor is an extension of bcbio-nextgen to visualize its progress
Home-page: https://github.com/guillermo-carrasco/bcbio-nextgen-monitor
Author: Guillermo Carrasco
Author-email: guille.ch.88@gmail.com
License: UNKNOWN
Keywords: bcbio,bcbio-nextgen,bioinformatics,genomics
Platform: UNKNOWN
Requires-Dist: flask (>=0.10.1)
Requires-Dist: gevent (>=1.0)
Requires-Dist: graphviz
Requires-Dist: paramiko
Requires-Dist: pyyaml
Requires-Dist: requests
